pymaftools/__init__.py
pymaftools/core/CancerCellFractionTable.py
pymaftools/core/Clustering.py
pymaftools/core/Cohort.py
pymaftools/core/CopyNumberVariationTable.py
pymaftools/core/ExpressionTable.py
pymaftools/core/MAF.py
pymaftools/core/PairwiseMatrix.py
pymaftools/core/PivotTable.py
pymaftools/core/SignatureTable.py
pymaftools/core/SmallVariationTable.py
pymaftools/core/__init__.py
pymaftools/data/cytoBand.txt
pymaftools/data/protein_domains.csv
pymaftools/model/StackingModel.py
pymaftools/model/__init__.py
pymaftools/model/modelUtils.py
pymaftools/plot/BasePlot.py
pymaftools/plot/ColorManager.py
pymaftools/plot/FontManager.py
pymaftools/plot/LegendManager.py
pymaftools/plot/LollipopPlot.py
pymaftools/plot/MethodsPlot.py
pymaftools/plot/ModelPlot.py
pymaftools/plot/OncoPlot.py
pymaftools/plot/PivotTablePlot.py
pymaftools/plot/__init__.py
pymaftools/utils/__init__.py
pymaftools/utils/geneinfo.py
pymaftools/utils/geneset.py
pymaftools/utils/reduction.py
pymaftools-0.3.0.dist-info/licenses/LICENSE
pymaftools-0.3.0.dist-info/METADATA
pymaftools-0.3.0.dist-info/WHEEL
pymaftools-0.3.0.dist-info/top_level.txt
pymaftools-0.3.0.dist-info/RECORD
