Metadata-Version: 2.4
Name: pymaftools
Version: 0.3.0
Summary: Python package for handling and analyzing Mutation Annotation Format (MAF) files.
Author-email: xu62u4u6 <199928ltyos@gmail.com>
License: MIT
Project-URL: Homepage, https://github.com/xu62u4u6/pymaftools
Requires-Python: >=3.10
License-File: LICENSE
Requires-Dist: pandas>2.0
Requires-Dist: numpy
Requires-Dist: networkx
Requires-Dist: matplotlib
Requires-Dist: seaborn
Requires-Dist: statannotations
Requires-Dist: scikit-learn
Requires-Dist: statsmodels
Requires-Dist: scipy
Requires-Dist: requests
Requires-Dist: beautifulsoup4
Requires-Dist: tqdm
Provides-Extra: test
Requires-Dist: pytest>=7.0.0; extra == "test"
Requires-Dist: pytest-cov>=4.0.0; extra == "test"
Requires-Dist: pytest-mock>=3.10.0; extra == "test"
Provides-Extra: dev
Requires-Dist: pytest>=7.0.0; extra == "dev"
Requires-Dist: pytest-cov>=4.0.0; extra == "dev"
Requires-Dist: pytest-mock>=3.10.0; extra == "dev"
Requires-Dist: build; extra == "dev"
Requires-Dist: twine; extra == "dev"
Dynamic: license-file
